README
setup.py
bin/rainbarrel
rainbarrel/__init__.py
rainbarrel/barrel.py
rainbarrel/event.py
rainbarrel/netjson.py
rainbarrel/plugin.py
rainbarrel.egg-info/PKG-INFO
rainbarrel.egg-info/SOURCES.txt
rainbarrel.egg-info/dependency_links.txt
rainbarrel.egg-info/requires.txt
rainbarrel.egg-info/top_level.txt
rainbarrel/plugins/__init__.py
rainbarrel/plugins/log_demand.py